<!DOCTYPE ui:UiBinder SYSTEM "http://dl.google.com/gwt/DTD/xhtml.ent">
<ui:UiBinder xmlns:ui="urn:ui:com.google.gwt.uibinder"
	xmlns:g="urn:import:com.google.gwt.user.client.ui">
	<ui:style>
		.important {
			font-weight: bold;
		}
		.artifactplate {
            box-shadow: inset 2px 2px 5px 1px #000000;
			background-color: ButtonShadow;
		}
		.groundplate {
			background: -webkit-gradient(linear, left top, right bottom, color-stop(0%, rgba(245, 246, 246, 1) ), color-stop(21%, rgba(219, 220, 226, 1) ),	color-stop(49%, rgba(184, 186, 198, 1) ),color-stop(80%, rgba(221, 223, 227, 1) ),	color-stop(100%, rgba(245, 246, 246, 1) ) );
            background: -webkit-linear-gradient(-45deg, rgba(245, 246, 246, 1) 0%,rgba(219, 220, 226, 1) 21%, rgba(184, 186, 198, 1) 49%,rgba(221, 223, 227, 1) 80%, rgba(245, 246, 246, 1) 100% );
            background: -moz-linear-gradient(-45deg, rgba(245, 246, 246, 1) 0%,rgba(219, 220, 226, 1) 21%, rgba(184, 186, 198, 1) 49%,rgba(221, 223, 227, 1) 80%, rgba(245, 246, 246, 1) 100% );
            background: -o-linear-gradient(-45deg, rgba(245, 246, 246, 1) 0%,rgba(219, 220, 226, 1) 21%, rgba(184, 186, 198, 1) 49%,rgba(221, 223, 227, 1) 80%, rgba(245, 246, 246, 1) 100% );
            filter: literal("progid:DXImageTransform.Microsoft.gradient(startColorstr = '#F8F8F8', endColorstr = '#A0A0A0')");
            margin-right: 2px;
            margin-bottom: 2px;
            float: left;
			padding: 10px;
			border-top: 1px solid #ddd;
			border-right: 2px solid #888;
			border-bottom: 2px solid #888;
			border-left: 1px solid #ccc;
			border-radius: 4px;
		}

        div-with-literal {  top: literal("expression(document.compatMode==\"CSS1Compat\" ? documentElement.scrollTop : document.body.scrollTop \\ 2)");}


	</ui:style>
		<g:HorizontalPanel title="Assemble an inventory item here. Press the Assemble button if the artifacts are fuldilled." styleName="{style.groundplate}" spacing="5">
			<g:VerticalPanel>
				<g:Cell horizontalAlignment="ALIGN_CENTER">
					<g:Image width="100px" height="100px" ui:field="image"/>
				</g:Cell>
				<g:Cell horizontalAlignment="ALIGN_CENTER" verticalAlignment="ALIGN_MIDDLE">
					<g:Button text="Assemble" ui:field="assembleButton"/>
				</g:Cell>
			</g:VerticalPanel>
			<g:Cell verticalAlignment="ALIGN_MIDDLE">
				<g:ScrollPanel height="" width="100px">
				<g:FlexTable width="" height="" styleName="{style.artifactplate}" ui:field="artifacts"/>
			</g:ScrollPanel>
			</g:Cell>
		</g:HorizontalPanel>
</ui:UiBinder>